pbio-0.0.4.dist-info/licenses/LICENSE
scio/__init__.py
scio/scio.py
pbio-0.0.4.dist-info/METADATA
pbio-0.0.4.dist-info/WHEEL
pbio-0.0.4.dist-info/top_level.txt
pbio-0.0.4.dist-info/RECORD
